hazenlib/ACRObject.py
hazenlib/HazenTask.py
hazenlib/__init__.py
hazenlib/_version.py
hazenlib/exceptions.py
hazenlib/logger.py
hazenlib/utils.py
hazenlib/data/relaxometry_params.py
hazenlib/data/relaxometry/Plate4_T1_signed
hazenlib/data/relaxometry/Plate4_T2
hazenlib/data/relaxometry/Plate5_T1_signed
hazenlib/data/relaxometry/Plate5_T2
hazenlib/tasks/__init__.py
hazenlib/tasks/acr_geometric_accuracy.py
hazenlib/tasks/acr_ghosting.py
hazenlib/tasks/acr_slice_position.py
hazenlib/tasks/acr_slice_thickness.py
hazenlib/tasks/acr_snr.py
hazenlib/tasks/acr_spatial_resolution.py
hazenlib/tasks/acr_uniformity.py
hazenlib/tasks/ghosting.py
hazenlib/tasks/relaxometry.py
hazenlib/tasks/slice_position.py
hazenlib/tasks/slice_width.py
hazenlib/tasks/snr.py
hazenlib/tasks/snr_map.py
hazenlib/tasks/spatial_resolution.py
hazenlib/tasks/uniformity.py
tests/__init__.py
tests/test_ACRObject.py
tests/test_acr_geometric_accuracy.py
tests/test_acr_ghosting.py
tests/test_acr_slice_position.py
tests/test_acr_slice_thickness.py
tests/test_acr_snr.py
tests/test_acr_spatial_resolution.py
tests/test_acr_uniformity.py
tests/test_ghosting.py
tests/test_hazenlib.py
tests/test_relaxometry.py
tests/test_slice_position.py
tests/test_slice_width.py
tests/test_snr.py
tests/test_snr_map.py
tests/test_spatial_resolution.py
tests/test_uniformity.py
tests/test_utils.py
hazen-1.3.4.dist-info/LICENSE.txt
hazen-1.3.4.dist-info/METADATA
hazen-1.3.4.dist-info/WHEEL
hazen-1.3.4.dist-info/entry_points.txt
hazen-1.3.4.dist-info/top_level.txt
hazen-1.3.4.dist-info/RECORD
