Metadata-Version: 2.2
Name: hazen
Version: 1.3.4
Summary: An automatic MRI QA tool
Home-page: https://bitbucket.org/gsttmri/hazen
Author: Shuaib, Haris
Author-email: mohammad_haris.shuaib@kcl.ac.uk
Requires-Python: <3.13,>=3.9
License-File: LICENSE.txt
Requires-Dist: pydicom==2.4.1
Requires-Dist: numpy>=1.26.0
Requires-Dist: matplotlib>=3.7.2
Requires-Dist: docopt==0.6.2
Requires-Dist: opencv-python-headless==4.8.1.78
Requires-Dist: scikit-image>=0.21.0
Requires-Dist: scipy>=1.11.3
Requires-Dist: imutils==0.5.4
Requires-Dist: colorlog==6.7.0
